restore/__init__.py
restore/admin.py
restore/apps.py
restore/common_commands.py
restore/management/__init__.py
restore/management/commands/__init__.py
restore/management/commands/restore.py
restore/migrations/__init__.py
restore/models.py
restore/tests.py
restore/views.py
django_restic_backup-0.12.0.dist-info/LICENSE
django_restic_backup-0.12.0.dist-info/METADATA
django_restic_backup-0.12.0.dist-info/WHEEL
django_restic_backup-0.12.0.dist-info/RECORD
