Metadata-Version: 2.3
Name: django-restic-backup
Version: 0.12.0
Summary: Restore files or/and database backup from an environment (backup server) with encrypted secret file after decrypting it (secret file is defined in settings.BACKUP_CONF_FILE
Author: Dedomainia
Requires-Python: >=3.10,<4.0
Classifier: Programming Language :: Python :: 3
Classifier: Programming Language :: Python :: 3.10
Classifier: Programming Language :: Python :: 3.11
Classifier: Programming Language :: Python :: 3.12
Classifier: Programming Language :: Python :: 3.13
Requires-Dist: django (>=4.2,<5.0)
Requires-Dist: pyyaml (>=6,<7)
